.travis.yml
MANIFEST.in
README.rst
base.cfg
buildout.cfg
setup.cfg
setup.py
test-4.0.x.cfg
test-4.1.x.cfg
test-4.2.x.cfg
test-4.3.x.cfg
test-4.4.x.cfg
travis.cfg
docs/FAQ.txt
docs/HISTORY.txt
docs/LICENSE.GPL
docs/LICENSE.txt
docs/TODO.txt
src/collective/__init__.py
src/collective.ckeditor.egg-info/PKG-INFO
src/collective.ckeditor.egg-info/SOURCES.txt
src/collective.ckeditor.egg-info/dependency_links.txt
src/collective.ckeditor.egg-info/entry_points.txt
src/collective.ckeditor.egg-info/namespace_packages.txt
src/collective.ckeditor.egg-info/not-zip-safe
src/collective.ckeditor.egg-info/requires.txt
src/collective.ckeditor.egg-info/top_level.txt
src/collective/ckeditor/__init__.py
src/collective/ckeditor/config.py
src/collective/ckeditor/configure.zcml
src/collective/ckeditor/rebuild_i18n.sh
src/collective/ckeditor/setuphandlers.py
src/collective/ckeditor/testing.py
src/collective/ckeditor/testing.zcml
src/collective/ckeditor/upgrades.py
src/collective/ckeditor/upgrades.zcml
src/collective/ckeditor/Extensions/Install.py
src/collective/ckeditor/Extensions/__init__.py
src/collective/ckeditor/_src/ckeditor/CHANGES.md
src/collective/ckeditor/_src/ckeditor/LICENSE.md
src/collective/ckeditor/_src/ckeditor/ckeditor.js
src/collective/ckeditor/_src/ckeditor/config.js
src/collective/ckeditor/_src/ckeditor/contents.css
src/collective/ckeditor/_src/ckeditor/styles.js
src/collective/ckeditor/_src/ckeditor/adapters/jquery.js
src/collective/ckeditor/_src/ckeditor/lang/_translationstatus.txt
src/collective/ckeditor/_src/ckeditor/lang/af.js
src/collective/ckeditor/_src/ckeditor/lang/ar.js
src/collective/ckeditor/_src/ckeditor/lang/az.js
src/collective/ckeditor/_src/ckeditor/lang/bg.js
src/collective/ckeditor/_src/ckeditor/lang/bn.js
src/collective/ckeditor/_src/ckeditor/lang/bs.js
src/collective/ckeditor/_src/ckeditor/lang/ca.js
src/collective/ckeditor/_src/ckeditor/lang/cs.js
src/collective/ckeditor/_src/ckeditor/lang/cy.js
src/collective/ckeditor/_src/ckeditor/lang/da.js
src/collective/ckeditor/_src/ckeditor/lang/de-ch.js
src/collective/ckeditor/_src/ckeditor/lang/de.js
src/collective/ckeditor/_src/ckeditor/lang/el.js
src/collective/ckeditor/_src/ckeditor/lang/en-au.js
src/collective/ckeditor/_src/ckeditor/lang/en-ca.js
src/collective/ckeditor/_src/ckeditor/lang/en-gb.js
src/collective/ckeditor/_src/ckeditor/lang/en.js
