Metadata-Version: 2.1
Name: collective.ckeditor
Version: 4.10.1
Summary: CKEditor for Plone
Home-page: https://github.com/collective/collective.ckeditor
Author: Alterway Solutions
Author-email: toutpt@gmail.com
License: GPL
Keywords: Plone CKeditor WYSIWYG
Platform: UNKNOWN
Classifier: Topic :: Software Development :: Libraries :: Python Modules
Classifier: License :: OSI Approved :: GNU General Public License (GPL)
Classifier: Operating System :: OS Independent
Classifier: Programming Language :: Python
Classifier: Environment :: Web Environment
Classifier: Framework :: Plone
Classifier: Framework :: Plone :: 4.0
Classifier: Framework :: Plone :: 4.1
Classifier: Framework :: Plone :: 4.2
Classifier: Framework :: Plone :: 4.3
Classifier: Programming Language :: Python :: 2.6
Classifier: Programming Language :: Python :: 2.7
Provides-Extra: test
